{"_invocation_id": "c2659246-9f88-4fbc-bfd3-533892c53590", "linked": {"0": {"name": "model.mental_health_analytics.dim_geography", "type": "model", "succ": [2, 3, 4, 5, 8]}, "1": {"name": "model.mental_health_analytics.stg_mental_health", "type": "model", "succ": [0, 2]}, "2": {"name": "model.mental_health_analytics.fact_mental_health", "type": "model", "succ": [6, 7, 8]}, "3": {"name": "test.mental_health_analytics.unique_dim_geography_geography_id.d6065c8c10", "type": "test"}, "4": {"name": "test.mental_health_analytics.not_null_dim_geography_geography_id.2e590571d0", "type": "test"}, "5": {"name": "test.mental_health_analytics.not_null_dim_geography_Country.5c88e1b535", "type": "test"}, "6": {"name": "test.mental_health_analytics.not_null_fact_mental_health_Timestamp.a3dff7df3f", "type": "test"}, "7": {"name": "test.mental_health_analytics.not_null_fact_mental_health_geography_id.addd9ee474", "type": "test"}, "8": {"name": "test.mental_health_analytics.relationships_fact_mental_health_geography_id__geography_id__ref_dim_geography_.33708b0c30", "type": "test"}}}